dbt_extractor-0.5.0.dist-info/METADATA
dbt_extractor-0.5.0.dist-info/WHEEL
dbt_extractor-0.5.0.dist-info/license_files/LICENSE
dbt_extractor/__init__.py
dbt_extractor/dbt_extractor.abi3.so
dbt_extractor-0.5.0.dist-info/RECORD
