Metadata-Version: 2.1
Name: dbt-extractor
Version: 0.5.0
Classifier: Programming Language :: Rust
Classifier: Development Status :: 5 - Production/Stable
Classifier: License :: OSI Approved :: Apache Software License
Classifier: Operating System :: Microsoft :: Windows
Classifier: Operating System :: MacOS :: MacOS X
Classifier: Operating System :: POSIX :: Linux
License-File: LICENSE
Summary: A tool to analyze and extract information from Jinja used in dbt projects.
Home-Page: https://github.com/dbt-labs/dbt-parser-generator/
Author: dbt Labs, Nathaniel May, Peter Webb
Author-email: info@dbtlabs.com, nathaniel.may@dbtlabs.com, peter.webb@dbtlabs.com
License: Apache-2.0
Requires-Python: >=3.6.1
Project-URL: Source Code, https://github.com/dbt-labs/dbt-parser-generator/
